itential_mcp/__init__.py
itential_mcp/__main__.py
itential_mcp/app.py
itential_mcp/defaults.py
itential_mcp/bindings/__init__.py
itential_mcp/bindings/endpoint.py
itential_mcp/bindings/service.py
itential_mcp/cli/__init__.py
itential_mcp/cli/argument_groups.py
itential_mcp/cli/parser.py
itential_mcp/cli/terminal.py
itential_mcp/config/__init__.py
itential_mcp/config/converters.py
itential_mcp/config/loaders.py
itential_mcp/config/models.py
itential_mcp/config/validators.py
itential_mcp/core/__init__.py
itential_mcp/core/env.py
itential_mcp/core/errors.py
itential_mcp/core/exceptions.py
itential_mcp/core/heuristics.py
itential_mcp/core/logging.py
itential_mcp/core/metadata.py
itential_mcp/middleware/bindings.py
itential_mcp/middleware/serialization.py
itential_mcp/models/adapters.py
itential_mcp/models/applications.py
itential_mcp/models/command_templates.py
itential_mcp/models/compliance_plans.py
itential_mcp/models/compliance_reports.py
itential_mcp/models/configuration_manager.py
itential_mcp/models/device_groups.py
itential_mcp/models/devices.py
itential_mcp/models/gateway_manager.py
itential_mcp/models/health.py
itential_mcp/models/integrations.py
itential_mcp/models/lifecycle_manager.py
itential_mcp/models/operations_manager.py
itential_mcp/models/projects.py
itential_mcp/models/templates.py
itential_mcp/models/workflow_engine.py
itential_mcp/platform/__init__.py
itential_mcp/platform/client.py
itential_mcp/platform/response.py
itential_mcp/platform/services/__init__.py
itential_mcp/platform/services/adapters.py
itential_mcp/platform/services/applications.py
itential_mcp/platform/services/automation_studio.py
itential_mcp/platform/services/configuration_manager.py
itential_mcp/platform/services/gateway_manager.py
itential_mcp/platform/services/health.py
itential_mcp/platform/services/integrations.py
itential_mcp/platform/services/lifecycle_manager.py
itential_mcp/platform/services/mop.py
itential_mcp/platform/services/operations_manager.py
itential_mcp-0.11.1.dist-info/METADATA
itential_mcp-0.11.1.dist-info/WHEEL
itential_mcp-0.11.1.dist-info/entry_points.txt
itential_mcp-0.11.1.dist-info/licenses/LICENSE
itential_mcp-0.11.1.dist-info/licenses/NOTICE
itential_mcp-0.11.1.dist-info/RECORD
