Metadata-Version: 2.4
Name: itential-mcp
Version: 0.11.1
Summary: Itential MCP Server
Project-URL: Homepage, https://itential.com
Project-URL: Repository, https://github.com/itential/itential-mcp
Project-URL: Documentation, https://github.com/itential/itential-mcp
Author-email: Itential <opensource@itential.com>
License-Expression: GPL-3.0-or-later
License-File: LICENSE
License-File: NOTICE
Keywords: agent,fastmcp,llm,mcp,mcp client,mcp server,model context protocol
Classifier: Intended Audience :: Developers
Classifier: License :: OSI Approved :: GNU General Public License v3 or later (GPLv3+)
Classifier: Programming Language :: Python :: 3.10
Classifier: Programming Language :: Python :: 3.11
Classifier: Programming Language :: Python :: 3.12
Classifier: Programming Language :: Python :: 3.13
Classifier: Topic :: Scientific/Engineering :: Artificial Intelligence
Classifier: Typing :: Typed
Requires-Python: >=3.10
Requires-Dist: fastmcp
Requires-Dist: ipsdk>=0.7.0
Requires-Dist: toon-python
Requires-Dist: wsproto
